payu/__init__.py
payu/_version.py
payu/backports.py
payu/branch.py
payu/calendar.py
payu/cli.py
payu/envmod.py
payu/experiment.py
payu/fsops.py
payu/git_utils.py
payu/laboratory.py
payu/manifest.py
payu/metadata.py
payu/namcouple.py
payu/runlog.py
payu/status.py
payu/sync.py
payu/telemetry.py
payu/models/__init__.py
payu/models/access.py
payu/models/access_esm1p6.py
payu/models/accessom2.py
payu/models/cable.py
payu/models/cesm_cmeps.py
payu/models/cice.py
payu/models/cice5.py
payu/models/fms.py
payu/models/gold.py
payu/models/mitgcm.py
payu/models/model.py
payu/models/mom.py
payu/models/mom6.py
payu/models/mom_mixin.py
payu/models/nemo.py
payu/models/oasis.py
payu/models/qgcm.py
payu/models/roms.py
payu/models/staged_cable.py
payu/models/test.py
payu/models/um.py
payu/models/ww3.py
payu/models/yatm.py
payu/profilers/__init__.py
payu/profilers/darshan.py
payu/profilers/gprof.py
payu/profilers/oss.py
payu/profilers/profiler.py
payu/schedulers/__init__.py
payu/schedulers/pbs.py
payu/schedulers/scheduler.py
payu/schedulers/slurm.py
payu/subcommands/__init__.py
payu/subcommands/archive_cmd.py
payu/subcommands/args.py
payu/subcommands/branch_cmd.py
payu/subcommands/build_cmd.py
payu/subcommands/checkout_cmd.py
payu/subcommands/clone_cmd.py
payu/subcommands/collate_cmd.py
payu/subcommands/ghsetup_cmd.py
payu/subcommands/init_cmd.py
payu/subcommands/list_cmd.py
payu/subcommands/profile_cmd.py
payu/subcommands/push_cmd.py
payu/subcommands/run_cmd.py
payu/subcommands/setup_cmd.py
payu/subcommands/status_cmd.py
payu/subcommands/sweep_cmd.py
payu/subcommands/sync_cmd.py
payu-1.2.0.dist-info/licenses/AUTHORS
payu-1.2.0.dist-info/licenses/LICENSE
payu-1.2.0.dist-info/licenses/NOTICE
payu-1.2.0.dist-info/METADATA
payu-1.2.0.dist-info/WHEEL
payu-1.2.0.dist-info/entry_points.txt
payu-1.2.0.dist-info/top_level.txt
payu-1.2.0.dist-info/RECORD
