Metadata-Version: 2.4
Name: payu
Version: 1.2.0
Summary: A climate model workflow manager for supercomputing environments
Author-email: Marshall Ward <python@marshallward.org>
Maintainer-email: ACCESS-NRI <access.nri@anu.edu.au>
License: Apache-2.0
Keywords: climate model,workflow
Classifier: Development Status :: 4 - Beta
Classifier: License :: OSI Approved :: Apache Software License
Classifier: Operating System :: POSIX :: Linux
Classifier: Programming Language :: Python :: 3
Classifier: Topic :: Utilities
License-File: LICENSE
License-File: NOTICE
License-File: AUTHORS
Requires-Dist: f90nml>=0.16
Requires-Dist: yamanifest>=0.3.4
Requires-Dist: PyYAML
Requires-Dist: requests
Requires-Dist: python-dateutil
Requires-Dist: tenacity>=8.0.0
Requires-Dist: cftime
Requires-Dist: GitPython>=3.1.40
Requires-Dist: ruamel.yaml>=0.18.5
Requires-Dist: packaging
Requires-Dist: netCDF4
Requires-Dist: jsonschema
Provides-Extra: test
Requires-Dist: pytest; extra == "test"
Requires-Dist: pylint; extra == "test"
Requires-Dist: Sphinx; extra == "test"
Requires-Dist: pytest-cov; extra == "test"
Requires-Dist: mnctools; extra == "test"
Provides-Extra: mitgcm
Requires-Dist: mnctools>=0.2; extra == "mitgcm"
Dynamic: license-file
